cached_property.py
cached_property-1.4.3.dist-info/DESCRIPTION.rst
cached_property-1.4.3.dist-info/METADATA
cached_property-1.4.3.dist-info/RECORD
cached_property-1.4.3.dist-info/WHEEL
cached_property-1.4.3.dist-info/metadata.json
cached_property-1.4.3.dist-info/top_level.txt
