Metadata-Version: 1.1
Name: cached-property
Version: 1.4.3
Summary: A decorator for caching properties in classes.
Home-page: https://github.com/pydanny/cached-property
Author: Daniel Greenfeld
Author-email: pydanny@gmail.com
License: BSD
Keywords: cached-property
Platform: UNKNOWN
Classifier: Development Status :: 5 - Production/Stable
Classifier: Intended Audience :: Developers
Classifier: License :: OSI Approved :: BSD License
Classifier: Natural Language :: English
Classifier: Programming Language :: Python :: 2
Classifier: Programming Language :: Python :: 2.7
Classifier: Programming Language :: Python :: 3
Classifier: Programming Language :: Python :: 3.3
Classifier: Programming Language :: Python :: 3.4
Classifier: Programming Language :: Python :: 3.5
Classifier: Programming Language :: Python :: 3.6
